License.txt
README.md
setup.py
EulersMethod/__init__.py
EulersMethod/euler.py
EulersMethod/eulertests.py
eulers_method.egg-info/PKG-INFO
eulers_method.egg-info/SOURCES.txt
eulers_method.egg-info/dependency_links.txt
eulers_method.egg-info/top_level.txt