Metadata-Version: 2.1
Name: eulers-method
Version: 0.0.1
Summary: Approximate the result function of a (simple) differential equation.
Author: Olli Glorioso
Author-email: olli.glorioso@gmail.com
License-File: License.txt
